trackit_vcs/base.py
trackit_vcs/cli.py
trackit_vcs/data.py
trackit_vcs/diffs.py
trackit_vcs-1.0.1.dist-info/licenses/LICENSE
trackit_vcs-1.0.1.dist-info/METADATA
trackit_vcs-1.0.1.dist-info/WHEEL
trackit_vcs-1.0.1.dist-info/entry_points.txt
trackit_vcs-1.0.1.dist-info/top_level.txt
trackit_vcs-1.0.1.dist-info/RECORD
