Metadata-Version: 2.4
Name: trackit-vcs
Version: 1.0.1
Summary: TrackIt is a basic version control system inspired by Git. It provides functionalities for creating commits, branches, tags, merging branches, and more.
Author-email: Shreyash Thengne <shreyashthengne@gmail.com>
Project-URL: Homepage, https://github.com/ShreyashThengne/trackIt
Project-URL: Repository, https://github.com/ShreyashThengne/trackIt
Project-URL: Issues, https://github.com/ShreyashThengne/trackIt/issues
Keywords: version control,personal version control,git,cli
Classifier: Development Status :: 4 - Beta
Classifier: Environment :: Console
Classifier: Intended Audience :: Developers
Classifier: Operating System :: Microsoft :: Windows
Classifier: Programming Language :: Python :: 3
Classifier: Programming Language :: Python :: 3.12
Classifier: Topic :: Software Development :: Version Control
Requires-Python: >=3.12
License-File: LICENSE
Dynamic: license-file
